setup.py
monika/__init__.py
monika.egg-info/PKG-INFO
monika.egg-info/SOURCES.txt
monika.egg-info/dependency_links.txt
monika.egg-info/top_level.txt