Metadata-Version: 1.1
Name: monika
Version: 0.0.1a0
Summary: Build modular Discord bots with ease.
Home-page: http://just-monika.club
Author: Kira Evans
Author-email: contact@kne42.me
License: Modified BSD
Download-URL: https://github.com/just-monika/just-monika
Platform: UNKNOWN
